[
  {
    "university": "National University of Technology (NUTECH), Islamabad",
    "program_title": "Spring 2026 Undergraduate Admissions",
    "publish_date": "Friday, March 06, 2026",
    "last_date": "Monday, May 18, 2026",
    "details_link": "https://nutech.edu.pk/admissions/",
    "programs_offered": [
      "BS Artificial Intelligence (BS AI)",
      "BS Civil Engineering (BS CE)",
      "BS Computer Engineering (BS CEN)",
      "BS Computer Science (BS CS)",
      "BS Cyber Security (BS CY)",
      "BS Electrical Engineering (BS EE)",
      "BS Information Technology (BS IT)",
      "BS Mechanical Engineering (BS ME)",
      "BS Software Engineering (BS SE)"
    ]
  }
]